setup.py
message_server_tchka.egg-info/PKG-INFO
message_server_tchka.egg-info/SOURCES.txt
message_server_tchka.egg-info/dependency_links.txt
message_server_tchka.egg-info/requires.txt
message_server_tchka.egg-info/top_level.txt
server/__init__.py
server/add_user.py
server/common_oop.py
server/config_window.py
server/database.py
server/decos.py
server/descriptors.py
server/errors.py
server/main_window.py
server/metaclasses.py
server/remove_user.py
server/server_oop.py
server/stat_window.py