Metadata-Version: 1.0
Name: message-server-tchka
Version: 1.0.0
Summary: OneMore Message Server
Home-page: UNKNOWN
Author: Elena Nikolaeva
Author-email: tchka777@gmail.com
License: UNKNOWN
Platform: UNKNOWN
